aurmessage/__init__.py
aurmessage/messager.py
aurmessage/mpmc.py
aurmessage-0.0.1.dist-info/METADATA
aurmessage-0.0.1.dist-info/WHEEL
aurmessage-0.0.1.dist-info/top_level.txt
aurmessage-0.0.1.dist-info/RECORD
